myra_eucaptcha/__init__.py
myra_eucaptcha/client.py
myra_eucaptcha/config.py
myra_eucaptcha/exceptions.py
myra_eucaptcha/models.py
myra_eucaptcha-0.1.5.dist-info/licenses/LICENSE
myra_eucaptcha-0.1.5.dist-info/METADATA
myra_eucaptcha-0.1.5.dist-info/WHEEL
myra_eucaptcha-0.1.5.dist-info/top_level.txt
myra_eucaptcha-0.1.5.dist-info/RECORD
