Metadata-Version: 2.4
Name: myra-eucaptcha
Version: 0.1.5
Summary: EU captcha protects your website/API against abuse like form spam and credential stuffing
Author-email: Myra Security GmbH <info@myrasecurity.com>
License: Copyright 2026 Myra Security GmbH
Project-URL: Homepage, https://www.eu-captcha.eu/
Project-URL: Documentation, https://docs.eu-captcha.eu/
Project-URL: Source, https://github.com/Myra-Security-GmbH/eu-captcha-python/
Project-URL: Issues, https://github.com/Myra-Security-GmbH/eu-captcha-python/issues/
Project-URL: Security, https://www.myrasecurity.com/en/responsible-disclosure-myra/
Classifier: Development Status :: 5 - Production/Stable
Classifier: Intended Audience :: Developers
Classifier: Intended Audience :: Information Technology
Classifier: Intended Audience :: System Administrators
Classifier: Topic :: Internet :: WWW/HTTP
Classifier: Topic :: Internet :: WWW/HTTP :: Dynamic Content
Classifier: Topic :: Security
Classifier: Topic :: Software Development :: Libraries
Classifier: Topic :: Software Development :: Libraries :: Python Modules
Classifier: License :: Other/Proprietary License
Classifier: Programming Language :: Python
Classifier: Programming Language :: Python :: 3
Classifier: Programming Language :: Python :: 3 :: Only
Classifier: Programming Language :: Python :: 3.9
Classifier: Programming Language :: Python :: 3.10
Classifier: Programming Language :: Python :: 3.11
Classifier: Programming Language :: Python :: 3.12
Classifier: Programming Language :: Python :: 3.13
Classifier: Programming Language :: Python :: 3.14
Classifier: Environment :: Web Environment
Classifier: Typing :: Typed
Classifier: Framework :: AsyncIO
Requires-Python: >=3.9
License-File: LICENSE
Requires-Dist: httpx>=0.25
Dynamic: license-file
